rfa_toolbox/__init__.py
rfa_toolbox/architectures/__init__.py
rfa_toolbox/architectures/resnet.py
rfa_toolbox/architectures/vgg.py
rfa_toolbox/domain.py
rfa_toolbox/encodings/__init__.py
rfa_toolbox/encodings/pytorch/__init__.py
rfa_toolbox/encodings/pytorch/domain.py
rfa_toolbox/encodings/pytorch/ingest_architecture.py
rfa_toolbox/encodings/pytorch/intermediate_graph.py
rfa_toolbox/encodings/pytorch/layer_handlers.py
rfa_toolbox/encodings/pytorch/substitutors.py
rfa_toolbox/encodings/pytorch/utils.py
rfa_toolbox/encodings/tensorflow_keras/__init__.py
rfa_toolbox/encodings/tensorflow_keras/ingest_architecture.py
rfa_toolbox/encodings/tensorflow_keras/layer_handlers.py
rfa_toolbox/graphs.py
rfa_toolbox/test_graphviz.py
rfa_toolbox/utils/__init__.py
rfa_toolbox/utils/graph_utils.py
rfa_toolbox/vizualize.py
rfa_toolbox-1.7.0.dist-info/LICENSE
rfa_toolbox-1.7.0.dist-info/WHEEL
rfa_toolbox-1.7.0.dist-info/METADATA
rfa_toolbox-1.7.0.dist-info/RECORD
