Metadata-Version: 2.1
Name: rfa-toolbox
Version: 1.7.0
Summary: A toolbox for analyzing the receptive field expansion in neural networks.
Home-page: https://github.com/MLRichter/receptive_field_analysis_toolbox
License: MIT
Author: Mats L. Richter
Author-email: matrichter@uni-osnabrueck.de
Requires-Python: >=3.7,<3.11
Classifier: Development Status :: 2 - Pre-Alpha
Classifier: Intended Audience :: Developers
Classifier: License :: OSI Approved :: MIT License
Classifier: Natural Language :: English
Classifier: Operating System :: OS Independent
Classifier: Programming Language :: Python :: 3
Classifier: Programming Language :: Python :: 3.10
Classifier: Programming Language :: Python :: 3.7
Classifier: Programming Language :: Python :: 3.8
Classifier: Programming Language :: Python :: 3.9
Classifier: Topic :: Software Development :: Libraries
Provides-Extra: docs
Requires-Dist: Sphinx (>=4.0.0,<5.0.0); extra == "docs"
Requires-Dist: attrs (>=21.2.0,<22.0.0)
Requires-Dist: graphviz (>=0.19.1,<0.20.0)
Requires-Dist: myst-parser (>=0.17.0,<0.18.0); extra == "docs"
Requires-Dist: numpy (>=1.21.4,<2.0.0)
Requires-Dist: sphinx-rtd-theme (>=1.0.0,<2.0.0); extra == "docs"
Requires-Dist: tqdm (>=4.62.3,<5.0.0)
Project-URL: Bug Tracker, https://github.com/MLRichter/rfa_toolbox/issues
Project-URL: Changelog, https://rfa_toolbox.readthedocs.io/changelog.html
Project-URL: Documentation, https://receptive_field_analysis_toolbox.readthedocs.io
Project-URL: Repository, https://github.com/MLRichter/receptive_field_analysis_toolbox
